LICENSE
MANIFEST.in
README.rst
setup.py
django_tsugi/LTIX.py
django_tsugi/__init__.py
django_tsugi/apps.py
django_tsugi/config.py
django_tsugi/cryptsession.py
django_tsugi/decorators.py
django_tsugi/example_settings.py
django_tsugi/middleware.py
django_tsugi/mixins.py
django_tsugi/urls.py
django_tsugi/views.py
django_tsugi.egg-info/PKG-INFO
django_tsugi.egg-info/SOURCES.txt
django_tsugi.egg-info/dependency_links.txt
django_tsugi.egg-info/requires.txt
django_tsugi.egg-info/top_level.txt