Metadata-Version: 1.1
Name: django-tsugi
Version: 0.1.12
Summary: Library code to help write Python Tools that use the Tsugi library to integrate into Learning Management Systems.
Home-page: https://github.com/tsugiproject/django-tsugi.git
Author: Charles Severance (Dr. Chuck)
Author-email: drchuck@learnxp.com
License: Apache License
Platform: UNKNOWN
Classifier: Environment :: Web Environment
Classifier: Framework :: Django
Classifier: Framework :: Django :: 2.1
Classifier: Intended Audience :: Developers
Classifier: License :: OSI Approved :: Apache Software License
Classifier: Operating System :: OS Independent
Classifier: Programming Language :: Python
Classifier: Programming Language :: Python :: 3.5
Classifier: Programming Language :: Python :: 3.6
Classifier: Topic :: Internet :: WWW/HTTP
Classifier: Topic :: Internet :: WWW/HTTP :: Dynamic Content
